llm_whisper_api.py
llm_whisper_api-0.1.1.dist-info/LICENSE
llm_whisper_api-0.1.1.dist-info/METADATA
llm_whisper_api-0.1.1.dist-info/WHEEL
llm_whisper_api-0.1.1.dist-info/entry_points.txt
llm_whisper_api-0.1.1.dist-info/top_level.txt
llm_whisper_api-0.1.1.dist-info/RECORD
