Metadata-Version: 2.1
Name: llm-whisper-api
Version: 0.1.1
Summary: Run transcriptions using the OpenAI Whisper API
Author: Simon Willison
License: Apache-2.0
Project-URL: Homepage, https://github.com/simonw/llm-whisper-api
Project-URL: Changelog, https://github.com/simonw/llm-whisper-api/releases
Project-URL: Issues, https://github.com/simonw/llm-whisper-api/issues
Project-URL: CI, https://github.com/simonw/llm-whisper-api/actions
Classifier: License :: OSI Approved :: Apache Software License
Requires-Python: >=3.9
License-File: LICENSE
Requires-Dist: llm
Requires-Dist: httpx
Provides-Extra: test
Requires-Dist: pytest ; extra == 'test'
Requires-Dist: pytest-httpx ; extra == 'test'
